tests/__init__.py
tests/api/__init__.py
tests/api/test_config_api_interface.py
tests/api/test_transaction_api_interface.py
transaction_service_quality_checker/__init__.py
transaction_service_quality_checker/addresses_map.py
transaction_service_quality_checker/app.py
transaction_service_quality_checker/app_block_creation.py
transaction_service_quality_checker/app_by_list.py
transaction_service_quality_checker/block_creation.py
transaction_service_quality_checker/comparer.py
transaction_service_quality_checker/metrics.py
transaction_service_quality_checker/api/__init__.py
transaction_service_quality_checker/api/api_interface.py
transaction_service_quality_checker/api/config_api_interface.py
transaction_service_quality_checker/api/etherscan_api_interface.py
transaction_service_quality_checker/api/transaction_api_interface.py
transaction_service_quality_checker-0.0.12.dist-info/METADATA
transaction_service_quality_checker-0.0.12.dist-info/WHEEL
transaction_service_quality_checker-0.0.12.dist-info/top_level.txt
transaction_service_quality_checker-0.0.12.dist-info/RECORD
