Metadata-Version: 2.1
Name: transaction-service-quality-checker
Version: 0.0.12
Summary: Transaction service quality checker
Home-page: https://github.com/keyperlabs/transaction-indexer-quality-checker.git
Author: Palmera
Author-email: general@palmeradao.xyz
